swis/__init__.py
swis/__main__.py
swis/swis.py
swis/version.py
swis/app/config.json
swis/app/favicon.ico
swis/app/index.html
swis/app/css/app.31d6cfe0.css
swis/app/css/vendor.4d013fe5.css
swis/app/fonts/KFOkCnqEu92Fr1MmgVxIIzQ.9391e6e2.woff
swis/app/fonts/KFOlCnqEu92Fr1MmEU9fBBc-.ddd11dab.woff
swis/app/fonts/KFOlCnqEu92Fr1MmSU5fBBc-.877b9231.woff
swis/app/fonts/KFOlCnqEu92Fr1MmWUlfBBc-.0344cc3c.woff
swis/app/fonts/KFOlCnqEu92Fr1MmYUtfBBc-.b555d228.woff
swis/app/fonts/KFOmCnqEu92Fr1Mu4mxM.9b78ea3b.woff
swis/app/fonts/flUhRq6tzZclQEJ-Vdg-IuiaDsNa.1dd1bb36.woff
swis/app/fonts/flUhRq6tzZclQEJ-Vdg-IuiaDsNcIhQ8tQ.f54bbe10.woff2
swis/app/icons/favicon-128x128.png
swis/app/icons/favicon-16x16.png
swis/app/icons/favicon-32x32.png
swis/app/icons/favicon-96x96.png
swis/app/js/129.b8b7ff5b.js
swis/app/js/3.a950df63.js
swis/app/js/384.4bbd9fc0.js
swis/app/js/614.20fb41c5.js
swis/app/js/750.7093ed53.js
swis/app/js/92.c03c435c.js
swis/app/js/923.f149aeb6.js
swis/app/js/app.5c682846.js
swis/app/js/vendor.eb707002.js
swis/assets/defaults.env
swis/assets/swis.service
swis/core/__init__.py
swis/core/config.py
swis/core/logger.py
swis/core/schemas.py
swis-0.6.1.dist-info/LICENSE
swis-0.6.1.dist-info/METADATA
swis-0.6.1.dist-info/WHEEL
swis-0.6.1.dist-info/entry_points.txt
swis-0.6.1.dist-info/top_level.txt
swis-0.6.1.dist-info/RECORD
