Metadata-Version: 2.1
Name: swis
Version: 0.6.1
Summary: Simple Web-based Interface for Scanner written in Python and JavaScript.
Home-page: https://github.com/rsusik/simple-web-based-interface-for-scanner
Author: Robert Susik
Author-email: robert.susik@gmail.com
License: GPLv3
Classifier: Programming Language :: Python
Classifier: Programming Language :: JavaScript
Classifier: Intended Audience :: End Users/Desktop
Classifier: Intended Audience :: System Administrators
Classifier: Operating System :: POSIX :: Linux
Classifier: Framework :: FastAPI
Classifier: Topic :: Internet :: WWW/HTTP
Classifier: Topic :: Printing
Classifier: Topic :: Multimedia :: Graphics :: Capture :: Scanners
Classifier: Topic :: Utilities
Requires-Python: >=3.8
License-File: LICENSE
Requires-Dist: fastapi~=0.7
Requires-Dist: uvicorn~=0.17
Requires-Dist: python-dotenv
Requires-Dist: python-multipart
Requires-Dist: websockets~=9.1
Requires-Dist: pydantic~=1.9
Requires-Dist: Pillow>=9
